pytest_httpdbg/__init__.py
pytest_httpdbg/plugin.py
pytest_httpdbg-0.9.1.dist-info/licenses/LICENSE
pytest_httpdbg-0.9.1.dist-info/METADATA
pytest_httpdbg-0.9.1.dist-info/WHEEL
pytest_httpdbg-0.9.1.dist-info/entry_points.txt
pytest_httpdbg-0.9.1.dist-info/top_level.txt
pytest_httpdbg-0.9.1.dist-info/RECORD
