Metadata-Version: 2.4
Name: pytest-httpdbg
Version: 0.9.1
Summary: A pytest plugin to record HTTP(S) requests with stack trace.
Author-email: cle-b <cle@tictac.pm>
License: Apache-2.0
Project-URL: Source, https://github.com/cle-b/pytest-httpdbg/
Project-URL: Documentation, https://httpdbg.readthedocs.io/
Classifier: Development Status :: 4 - Beta
Classifier: Environment :: Web Environment
Classifier: Intended Audience :: Developers
Classifier: License :: OSI Approved :: Apache Software License
Classifier: Operating System :: OS Independent
Classifier: Programming Language :: Python :: 3
Classifier: Topic :: Internet :: WWW/HTTP
Classifier: Topic :: Software Development :: Testing
Classifier: Framework :: Pytest
Requires-Python: >=3.9.0
License-File: LICENSE
Requires-Dist: httpdbg>=1.2.5
Requires-Dist: pytest>=7.0.0
Dynamic: license-file
